django_fakeinline-0.1.1.dist-info/DESCRIPTION.rst
django_fakeinline-0.1.1.dist-info/LICENSE.txt
django_fakeinline-0.1.1.dist-info/METADATA
django_fakeinline-0.1.1.dist-info/RECORD
django_fakeinline-0.1.1.dist-info/WHEEL
django_fakeinline-0.1.1.dist-info/metadata.json
django_fakeinline-0.1.1.dist-info/top_level.txt
fakeinline/__init__.py
fakeinline/apps.py
fakeinline/datastructures.py
fakeinline/models.py
fakeinline/templates/admin/edit_inline/fakeinline.html
fakeinline/tests/__init__.py
fakeinline/tests/admin.py
fakeinline/tests/apps.py
fakeinline/tests/models.py
fakeinline/tests/test_admin.py
fakeinline/tests/migrations/0001_initial.py
fakeinline/tests/migrations/__init__.py
