Metadata-Version: 2.0
Name: django-fakeinline
Version: 0.1.1
Summary: fakeinline provides enough of the methods and attributes to trick the Django Admin into displaying it when mounted as part of an inlines declaration on a ModelAdmin
Home-page: https://github.com/kezabelle/django-fakeinline
Author: Keryn Knight
Author-email: python-fakeinline@kerynknight.com
License: BSD License
Keywords: django inline admin fake
Platform: UNKNOWN
Classifier: Development Status :: 3 - Alpha
Classifier: Intended Audience :: Developers
Classifier: License :: OSI Approved :: BSD License
Classifier: Natural Language :: English
Classifier: Programming Language :: Python :: 2
Classifier: Programming Language :: Python :: 2.7
Classifier: Programming Language :: Python :: 3
Classifier: Programming Language :: Python :: 3.3
Classifier: Programming Language :: Python :: 3.4
Classifier: Programming Language :: Python :: 3.5
Classifier: Framework :: Django
Classifier: Framework :: Django :: 1.10
Classifier: Framework :: Django :: 1.8
Classifier: Framework :: Django :: 1.9
Requires-Dist: Django (>=1.8)
